<?xml version="1.0" encoding="UTF-8"?>
<!DOCTYPE mapper PUBLIC "-//mybatis.org//DTD Mapper 3.0//EN" "http://mybatis.org/dtd/mybatis-3-mapper.dtd">
<mapper namespace="com.yqwl.dao.PlotBuildMapper">
  <resultMap id="BaseResultMap" type="com.yqwl.pojo.PlotBuild">
    <!--
      WARNING - @mbggenerated
      This element is automatically generated by MyBatis Generator, do not modify.
    -->
    <id column="id" jdbcType="BIGINT" property="id" />
    <result column="building_id" jdbcType="BIGINT" property="building_id" />
    <result column="name" jdbcType="VARCHAR" property="name" />
    <result column="name_type" jdbcType="VARCHAR" property="name_type" />
    <result column="unit_num" jdbcType="INTEGER" property="unit_num" />
    <result column="total_floor" jdbcType="INTEGER" property="total_floor" />
  </resultMap>
  <sql id="Base_Column_List">
    <!--
      WARNING - @mbggenerated
      This element is automatically generated by MyBatis Generator, do not modify.
    -->
    `id`, `building_id`, `name`, `name_type`, `unit_num`, `total_floor`
  </sql>
  <select id="selectByPrimaryKey" parameterType="java.lang.Long" resultMap="BaseResultMap">
    <!--
      WARNING - @mbggenerated
      This element is automatically generated by MyBatis Generator, do not modify.
    -->
    select 
    <include refid="Base_Column_List" />
    from `t_plot_build`
    where `id` = #{id,jdbcType=BIGINT}
  </select>
  <delete id="deleteByPrimaryKey" parameterType="java.lang.Long">
    <!--
      WARNING - @mbggenerated
      This element is automatically generated by MyBatis Generator, do not modify.
    -->
    delete from `t_plot_build`
    where `id` = #{id,jdbcType=BIGINT}
  </delete>
  <insert id="insert" parameterType="com.yqwl.pojo.PlotBuild">
    <!--
      WARNING - @mbggenerated
      This element is automatically generated by MyBatis Generator, do not modify.
    -->
    <selectKey keyProperty="id" order="AFTER" resultType="java.lang.Long">
      SELECT LAST_INSERT_ID()
    </selectKey>
    insert into `t_plot_build` (`building_id`, `name`, `name_type`, 
      `unit_num`, `total_floor`)
    values (#{building_id,jdbcType=BIGINT}, #{name,jdbcType=VARCHAR}, #{name_type,jdbcType=VARCHAR}, 
      #{unit_num,jdbcType=INTEGER}, #{total_floor,jdbcType=INTEGER})
  </insert>
  <insert id="insertSelective" parameterType="com.yqwl.pojo.PlotBuild">
    <!--
      WARNING - @mbggenerated
      This element is automatically generated by MyBatis Generator, do not modify.
    -->
    <selectKey keyProperty="id" order="AFTER" resultType="java.lang.Long">
      SELECT LAST_INSERT_ID()
    </selectKey>
    insert into `t_plot_build`
    <trim prefix="(" suffix=")" suffixOverrides=",">
      <if test="building_id != null">
        `building_id`,
      </if>
      <if test="name != null">
        `name`,
      </if>
      <if test="name_type != null">
        `name_type`,
      </if>
      <if test="unit_num != null">
        `unit_num`,
      </if>
      <if test="total_floor != null">
        `total_floor`,
      </if>
    </trim>
    <trim prefix="values (" suffix=")" suffixOverrides=",">
      <if test="building_id != null">
        #{building_id,jdbcType=BIGINT},
      </if>
      <if test="name != null">
        #{name,jdbcType=VARCHAR},
      </if>
      <if test="name_type != null">
        #{name_type,jdbcType=VARCHAR},
      </if>
      <if test="unit_num != null">
        #{unit_num,jdbcType=INTEGER},
      </if>
      <if test="total_floor != null">
        #{total_floor,jdbcType=INTEGER},
      </if>
    </trim>
  </insert>
  <update id="updateByPrimaryKeySelective" parameterType="com.yqwl.pojo.PlotBuild">
    <!--
      WARNING - @mbggenerated
      This element is automatically generated by MyBatis Generator, do not modify.
    -->
    update `t_plot_build`
    <set>
      <if test="building_id != null">
        `building_id` = #{building_id,jdbcType=BIGINT},
      </if>
      <if test="name != null">
        `name` = #{name,jdbcType=VARCHAR},
      </if>
      <if test="name_type != null">
        `name_type` = #{name_type,jdbcType=VARCHAR},
      </if>
      <if test="unit_num != null">
        `unit_num` = #{unit_num,jdbcType=INTEGER},
      </if>
      <if test="total_floor != null">
        `total_floor` = #{total_floor,jdbcType=INTEGER},
      </if>
    </set>
    where `id` = #{id,jdbcType=BIGINT}
  </update>
  <update id="updateByPrimaryKey" parameterType="com.yqwl.pojo.PlotBuild">
    <!--
      WARNING - @mbggenerated
      This element is automatically generated by MyBatis Generator, do not modify.
    -->
    update `t_plot_build`
    set `building_id` = #{building_id,jdbcType=BIGINT},
      `name` = #{name,jdbcType=VARCHAR},
      `name_type` = #{name_type,jdbcType=VARCHAR},
      `unit_num` = #{unit_num,jdbcType=INTEGER},
      `total_floor` = #{total_floor,jdbcType=INTEGER}
    where `id` = #{id,jdbcType=BIGINT}
  </update>
</mapper>